[{"line":1,"elements":[{"line":3,"name":"","description":"","type":"background","keyword":"Background","steps":[]},{"line":8,"name":"Verify correct request to create a reservation receive 200","description":"","id":"verify-correct-request-to-create-a-reservation-receive-200","type":"scenario","keyword":"Scenario","steps":[{"name":"scenario init failed","result":{"duration":0,"error_message":"com.intuit.karate.exception.KarateException: createBooking.feature:8 - failed to construct class by name: karate-http.properties not found, aborting","status":"failed"},"match":{"location":"karate","arguments":[]},"keyword":"*","line":8}],"tags":[{"name":"@HappyPath","line":7}]}],"name":"restfulbooker\/createbooking\/createBooking.feature","description":"Create Booking","id":"create-booking","keyword":"Feature","uri":"restfulbooker\/createbooking\/createBooking.feature"}]